setup.py
activity_feed/__init__.py
activity_feed/_utils_speedups.c
activity_feed/app.py
activity_feed/connection.py
activity_feed/utils.py
activity_feed.egg-info/PKG-INFO
activity_feed.egg-info/SOURCES.txt
activity_feed.egg-info/dependency_links.txt
activity_feed.egg-info/requires.txt
activity_feed.egg-info/top_level.txt