Metadata-Version: 1.1
Name: activity-feed
Version: 2.6.3
Summary: An Activity Feed for python
Home-page: https://github.com/simonz05/activity-feed/
Author: Simon Zimmermann
Author-email: simon@insmo.com
License: MIT
Keywords: redis
Platform: any
Classifier: Development Status :: 2 - Pre-Alpha
Classifier: Intended Audience :: Developers
Classifier: License :: OSI Approved :: MIT License
Classifier: Operating System :: POSIX
Classifier: Programming Language :: Python
Classifier: Topic :: Software Development
Classifier: Topic :: Software Development :: Libraries
